{"stats":{"minecraft:used":{"minecraft:stone_sword":63},"minecraft:killed_by":{"in_your_world:hijitus_ataque":1},"minecraft:custom":{"minecraft:jump":209,"minecraft:time_since_rest":3458,"minecraft:deaths":2,"minecraft:damage_dealt":3735,"minecraft:crouch_one_cm":71,"minecraft:leave_game":1,"minecraft:play_time":66280,"minecraft:sprint_one_cm":55563,"minecraft:damage_taken":2435,"minecraft:time_since_death":0,"minecraft:walk_one_cm":19001,"minecraft:sneak_time":282,"minecraft:total_world_time":66280,"minecraft:mob_kills":2,"minecraft:fall_one_cm":2620,"minecraft:fly_one_cm":34362},"minecraft:killed":{"boiled_reimagined:the_boiled_one":1,"man:managgresive":1}},"DataVersion":3120}